lightllm/__init__.py
lightllm/common/__init__.py
lightllm/common/build_utils.py
lightllm/common/infer_utils.py
lightllm/common/int8kv_mem_manager.py
lightllm/common/mem_manager.py
lightllm/common/mem_utils.py
lightllm/common/ppl_int4kv_mem_manager.py
lightllm/common/ppl_int8kv_mem_manager.py
lightllm/common/req_manager.py
lightllm/common/basemodel/__init__.py
lightllm/common/basemodel/basemodel.py
lightllm/common/basemodel/infer_struct.py
lightllm/common/basemodel/splitfuse_infer_struct.py
lightllm/common/basemodel/cuda_kernel/__init__.py
lightllm/common/basemodel/cuda_kernel/fast_llm_wquant.py
lightllm/common/basemodel/cuda_kernel/lmdeploy_wquant.py
lightllm/common/basemodel/cuda_kernel/ppl_awquant.py
lightllm/common/basemodel/cuda_kernel/ppl_wquant.py
lightllm/common/basemodel/layer_infer/__init__.py
lightllm/common/basemodel/layer_infer/base_layer_infer.py
lightllm/common/basemodel/layer_infer/post_layer_infer.py
lightllm/common/basemodel/layer_infer/pre_layer_infer.py
lightllm/common/basemodel/layer_infer/transformer_layer_infer.py
lightllm/common/basemodel/layer_infer/template/__init__.py
lightllm/common/basemodel/layer_infer/template/post_layer_infer_template.py
lightllm/common/basemodel/layer_infer/template/pre_layer_infer_template.py
lightllm/common/basemodel/layer_infer/template/transformer_layer_infer_template.py
lightllm/common/basemodel/layer_infer/template/transformer_layer_infer_template_awquant.py
lightllm/common/basemodel/layer_infer/template/transformer_layer_infer_template_wquant.py
lightllm/common/basemodel/layer_weights/__init__.py
lightllm/common/basemodel/layer_weights/base_layer_weight.py
lightllm/common/basemodel/layer_weights/hf_load_utils.py
lightllm/common/basemodel/layer_weights/pre_and_post_layer_weight.py
lightllm/common/basemodel/layer_weights/transformer_layer_weight.py
lightllm/common/basemodel/triton_kernel/__init__.py
lightllm/common/basemodel/triton_kernel/apply_penalty.py
lightllm-0.0.1.dist-info/LICENSE
lightllm-0.0.1.dist-info/METADATA
lightllm-0.0.1.dist-info/WHEEL
lightllm-0.0.1.dist-info/top_level.txt
lightllm-0.0.1.dist-info/RECORD
