Metadata-Version: 2.1
Name: lightllm
Version: 0.0.1
Summary: lightllm for inference LLM
Home-page: 
Author: model toolchain
Author-email: 
Classifier: Programming Language :: Python :: 3
Classifier: Operating System :: POSIX :: Linux
Requires-Python: >=3.9
License-File: LICENSE
Requires-Dist: pyzmq
Requires-Dist: uvloop
Requires-Dist: torch
Requires-Dist: transformers
Requires-Dist: einops
Requires-Dist: packaging
Requires-Dist: rpyc
Requires-Dist: ninja
Requires-Dist: safetensors
Requires-Dist: triton
